django_tabler_theme/__init__.py
django_tabler_theme/apps.py
django_tabler_theme/conf.py
django_tabler_theme/context_processors.py
django_tabler_theme/management/__init__.py
django_tabler_theme/management/commands/__init__.py
django_tabler_theme/management/commands/tabler_check.py
django_tabler_theme/management/commands/tabler_copy.py
django_tabler_theme/management/commands/tabler_generate.py
django_tabler_theme/management/commands/tabler_setup.py
django_tabler_theme/static/tabler_theme/theme.css
django_tabler_theme/static/tabler_theme/theme.js
django_tabler_theme/templates/django_tabler_theme/management/dashboard.html
django_tabler_theme/templates/django_tabler_theme/management/form.html
django_tabler_theme/templates/django_tabler_theme/management/login.html
django_tabler_theme/templates/django_tabler_theme/management/page.html
django_tabler_theme/templates/django_tabler_theme/management/table.html
django_tabler_theme/templates/tabler_theme/_topnav.html
django_tabler_theme/templates/tabler_theme/base.html
django_tabler_theme/templatetags/__init__.py
django_tabler_theme/templatetags/tabler.py
django_tabler_theme-0.1.0.dist-info/licenses/LICENSE
django_tabler_theme-0.1.0.dist-info/METADATA
django_tabler_theme-0.1.0.dist-info/WHEEL
django_tabler_theme-0.1.0.dist-info/top_level.txt
django_tabler_theme-0.1.0.dist-info/RECORD
