Metadata-Version: 2.4
Name: django-tabler-theme
Version: 0.1.0
Summary: Reusable Django theme app using Tabler (Bootstrap 5) with templates, components, and helpers.
Author-email: Your Name <you@example.com>
License: MIT
Project-URL: Homepage, https://github.com/your-org/django-tabler-theme
Project-URL: Issues, https://github.com/your-org/django-tabler-theme/issues
Keywords: django,tabler,bootstrap,theme,templates
Classifier: Framework :: Django
Classifier: Framework :: Django :: 4.2
Classifier: Framework :: Django :: 5.0
Classifier: Programming Language :: Python :: 3
Classifier: Programming Language :: Python :: 3 :: Only
Classifier: License :: OSI Approved :: MIT License
Classifier: Operating System :: OS Independent
Requires-Python: >=3.10
License-File: LICENSE
Requires-Dist: Django>=4.2
Provides-Extra: test
Requires-Dist: pytest; extra == "test"
Requires-Dist: pytest-django; extra == "test"
Dynamic: license-file
